{"widget_positions":{"wp_inactive_widgets":["news-bulletin-layout-widget-2","news-bulletin-layout-widget-3","news-bulletin-layout-widget-4","news-bulletin-layout-widget-5","news-bulletin-layout-widget-6","news-bulletin-layout-widget-7","news_bulletin_category_column_widget-3","news_bulletin_3_column_widget-3","news_bulletin_category_tabbed_widget-4","social-widget-2","social-widget-3","social-widget-4","news-bulletin-latest-widget-2","news-bulletin-latest-widget-3","news-bulletin-latest-widget-5","news-bulletin-advertisement-widget-2","news-bulletin-advertisement-widget-3","news-bulletin-advertisement-widget-7","news-bulletin-slider-widget-3","recent-posts-3"],"advertisement":["news-bulletin-advertisement-widget-4"],"sidebar-1":{"1":"search-2","4":"recent-posts-2","5":"recent-comments-2","6":"archives-2","7":"categories-2","8":"meta-2"},"home-sections-1":["news-bulletin-layout-widget-8","news_bulletin_category_tabbed_widget-5","news-bulletin-advertisement-widget-5"],"home-sections":["news-bulletin-layout-widget-10","news_bulletin_category_column_widget-4","news-bulletin-slider-widget-4","news-bulletin-layout-widget-11","news-bulletin-advertisement-widget-6"],"home-sections-2":["news-bulletin-layout-widget-9","news_bulletin_3_column_widget-4"],"footer1":["news-bulletin-latest-widget-4"],"footer2":["recent-posts-4"],"footer3":["social-widget-5"],"footer4":[],"banner-sidebar":[],"array_version":3},"widget_options":{"news-bulletin-layout-widget":{"2":{"cat_id":109,"title":"Health News","post_number":8,"layout_type":"layout6"},"3":{"cat_id":"20","title":"Business News","post_number":8,"layout_type":"layout2"},"4":{"cat_id":"58","title":"Health News","post_number":6,"layout_type":"layout4"},"5":{"cat_id":"68","title":"Political News","post_number":4,"layout_type":"layout5"},"6":{"cat_id":"61","title":"Sport News","post_number":5,"layout_type":"layout3"},"7":{"cat_id":"16","title":"Fashion News","post_number":6,"layout_type":"layout4"},"8":{"cat_id":109,"title":"News Title","post_number":7,"view":"View All","layout_type":"layout6"},"9":{"cat_id":61,"title":"Sports","post_number":5,"view":"View All","layout_type":"layout1"},"10":{"cat_id":29,"title":"Travel","post_number":5,"view":"View All","layout_type":"layout2"},"11":{"cat_id":115,"title":"Health","post_number":5,"view":"View All","layout_type":"layout5"},"_multiwidget":1},"news_bulletin_category_column_widget":{"3":{"category_id_1":36,"category_id_2":27,"post_number":5,"view":"View All"},"4":{"category_id_1":27,"category_id_2":68,"post_number":5,"view":"View All"},"_multiwidget":1},"news_bulletin_3_column_widget":{"3":{"category_id_1":16,"category_id_2":58,"category_id_3":28,"view":"View All","post_number":5},"4":{"category_id_1":58,"category_id_2":115,"category_id_3":113,"view":"View All","post_number":5},"_multiwidget":1},"news_bulletin_category_tabbed_widget":{"4":{"category_id":["16","20"],"widget_title":"Popular News","post_number":5},"5":{"category_id":["16","20"],"widget_title":"Popular News","post_number":5},"_multiwidget":1},"social-widget":{"2":{"title":"Follow Us","facebook":"http:\/\/Like%20us%20on%20Facebook","twitter":"http:\/\/Follow%20us%20on%20Twitter","googleplus":"http:\/\/Follow%20us%20on%20Instagram","linkedin":"http:\/\/Get%20connected%20with%20us%20in%20LinkedIn","youtube":"http:\/\/Subscribe%20us"},"3":{"title":"Follow US","facebook":"http:\/\/Like%20us%20on%20Facebook","twitter":"http:\/\/Follow%20us%20on%20Twitter","googleplus":"http:\/\/Follow%20us%20on%20Instagram","linkedin":"http:\/\/Get%20connected%20with%20us%20","youtube":"http:\/\/Subscribe%20us"},"4":{"title":"Follow Us","facebook":"#","twitter":"#","googleplus":"#","linkedin":"#","youtube":"#"},"5":{"title":"Follow Us","facebook":"#","twitter":"#","googleplus":"#","linkedin":"#","youtube":"#"},"_multiwidget":1},"news-bulletin-latest-widget":{"2":{"cat_id":"29","title":"Popular News"},"3":{"cat_id":"16","title":"Latest News"},"4":{"cat_id":103,"title":"Popular News"},"5":{"cat_id":113,"title":"Popular News"},"_multiwidget":1},"news-bulletin-advertisement-widget":{"2":{"title":"","ad_link":"","ad_img":"https:\/\/preview.amplethemes.com\/news-bulletin\/wp-content\/uploads\/sites\/92\/2021\/06\/Untitled-2.png"},"3":{"title":"Advertisement","ad_link":"http:\/\/www.amplethemes.com","ad_img":"https:\/\/preview.amplethemes.com\/news-bulletin\/wp-content\/uploads\/sites\/92\/2021\/06\/ad.jpg"},"4":{"title":"","ad_link":"http:\/\/www.amplethemes.com\/downloads\/news-bulletin-pro","ad_img":"https:\/\/preview.amplethemes.com\/news-bulletin-pro\/wp-content\/uploads\/sites\/93\/2021\/06\/uyu-2.png"},"5":{"title":"","ad_link":"","ad_img":"https:\/\/preview.amplethemes.com\/news-bulletin-pro\/wp-content\/uploads\/sites\/93\/2021\/06\/Untitled-2.jpg"},"6":{"title":"","ad_link":"","ad_img":"https:\/\/preview.amplethemes.com\/news-bulletin-pro\/wp-content\/uploads\/sites\/93\/2021\/06\/uyu-2.png"},"7":{"title":"Advertisement","ad_link":"","ad_img":"https:\/\/preview.amplethemes.com\/news-bulletin-pro\/wp-content\/uploads\/sites\/93\/2021\/06\/ad.jpg"},"_multiwidget":1},"news-bulletin-slider-widget":{"3":[],"4":{"cat_id":113,"title":"Feature","post_number":5,"view":"View All"},"_multiwidget":1},"recent-posts":{"2":{"title":"","number":5},"3":{"title":"Latest posts","number":6,"show_date":true},"4":{"title":"latest News","number":7,"show_date":true},"_multiwidget":1},"search":{"2":{"title":""},"_multiwidget":1},"recent-comments":{"2":{"title":"","number":5},"_multiwidget":1},"archives":{"2":{"title":"","count":0,"dropdown":0},"_multiwidget":1},"categories":{"2":{"title":"","count":0,"hierarchical":0,"dropdown":0},"_multiwidget":1},"meta":{"2":{"title":""},"_multiwidget":1}}}